salduba/__init__.py
salduba/py.typed
salduba/weather/__init__.py
salduba/weather/cli.py
salduba_poetry_sample-0.1.0.dist-info/LICENSE
salduba_poetry_sample-0.1.0.dist-info/METADATA
salduba_poetry_sample-0.1.0.dist-info/WHEEL
salduba_poetry_sample-0.1.0.dist-info/entry_points.txt
salduba_poetry_sample-0.1.0.dist-info/RECORD
