Metadata-Version: 2.1
Name: salduba_poetry_sample
Version: 0.1.0
Summary: 
License: LICENSE
Author: Miguel Pinilla
Author-email: miguel.pinilla@saldubatech.com
Requires-Python: >=3.11,<4.0
Classifier: Development Status :: 2 - Pre-Alpha
Classifier: License :: OSI Approved :: MIT License
Classifier: License :: Other/Proprietary License
Classifier: Programming Language :: Python :: 3
Classifier: Programming Language :: Python :: 3.11
Classifier: Programming Language :: Python :: 3.12
Classifier: Typing :: Typed
Requires-Dist: click (>=8.1.7,<9.0.0)
Requires-Dist: requests (>=2.31.0,<3.0.0)
